octo_pipeline_python/backends/conan/__init__.py
octo_pipeline_python/backends/conan/conan_backend.py
octo_pipeline_python/backends/conan/actions/__init__.py
octo_pipeline_python/backends/conan/actions/conan_build.py
octo_pipeline_python/backends/conan/actions/conan_consume.py
octo_pipeline_python/backends/conan/actions/conan_deploy.py
octo_pipeline_python/backends/conan/actions/conan_install.py
octo_pipeline_python/backends/conan/actions/conan_package.py
octo_pipeline_python/backends/conan/actions/conan_source.py
octo_pipeline_python/backends/conan/actions/conan_unittests.py
octo_pipeline_python/backends/conan/common/__init__.py
octo_pipeline_python/backends/conan/common/package_finder.py
octo_pipeline_python/backends/conan/common/pattern_finder.py
octo_pipeline_python/backends/conan/models/__init__.py
octo_pipeline_python/backends/conan/models/conan_configuration.py
octo_pipeline_python/backends/conan/models/conan_model.py
octo_pipeline_backend_conan_python-1.3.2.dist-info/LICENSE.txt
octo_pipeline_backend_conan_python-1.3.2.dist-info/METADATA
octo_pipeline_backend_conan_python-1.3.2.dist-info/README.md
octo_pipeline_backend_conan_python-1.3.2.dist-info/WHEEL
octo_pipeline_backend_conan_python-1.3.2.dist-info/top_level.txt
octo_pipeline_backend_conan_python-1.3.2.dist-info/RECORD
